LICENSE.txt
README.md
setup.cfg
setup.py
Spanners/Digger.py
Spanners/Downloader.py
Spanners/Errors.py
Spanners/Executor.py
Spanners/GoogleMaps.py
Spanners/IdentityCache.py
Spanners/Squirrel.py
Spanners/Treeify.py
Spanners/__init__.py
Spanners.egg-info/PKG-INFO
Spanners.egg-info/SOURCES.txt
Spanners.egg-info/dependency_links.txt
Spanners.egg-info/requires.txt
Spanners.egg-info/top_level.txt
bin/dig.py
bin/squirrel.py
bin/treeify.py