Metadata-Version: 2.4
Name: Spanners
Version: 1.28
Home-page: https://github.com/eddo888/Spanners
Download-URL: https://github.com/eddo888/Spanners/archive/1.28.tar.gz
Author: David Edson
Author-email: eddo888@tpg.com.au
License: MIT
License-File: LICENSE.txt
Requires-Dist: credstash==1.14.0
Requires-Dist: xmltodict
Requires-Dist: googlemaps
Requires-Dist: asciitree
Requires-Dist: bs4
Requires-Dist: arrow
Requires-Dist: Baubles
Requires-Dist: Perdy
Requires-Dist: Argumental
Dynamic: author
Dynamic: author-email
Dynamic: description
Dynamic: description-content-type
Dynamic: download-url
Dynamic: home-page
Dynamic: license
Dynamic: license-file
Dynamic: requires-dist
